progja/__init__.py
progja/data.py
progja/decks.py
progja/entities.py
progja/kanji.py
progja/logging.py
progja/paths.py
progja/sentences.py
progja/tokenizer.py
progja/words.py
progja/data/deck-style.css
progja/data/entities.csv
progja/data/kanji-progressions.json
progja/data/kanji.csv
progja/data/path-level-1.csv
progja/data/path-level-2.csv
progja/data/path-level-3.csv
progja/data/path-level-4.csv
progja/data/path-level-5.csv
progja/data/sentence-compositions.json
progja/data/sentence-progressions.json
progja/data/sentence-translations.csv
progja/data/sentences.csv
progja/data/word-compositions.json
progja/data/word-definitions-common.csv
progja/data/word-definitions-uncommon.csv
progja/data/word-progressions.json
progja/data/words-common.csv
progja/data/words-uncommon.csv
progja-0.1.1.dist-info/LICENSE
progja-0.1.1.dist-info/METADATA
progja-0.1.1.dist-info/WHEEL
progja-0.1.1.dist-info/top_level.txt
progja-0.1.1.dist-info/RECORD
