Metadata-Version: 2.1
Name: progja
Version: 0.1.1
Summary: Data and tools for those studying the Japanese language.
Home-page: https://gitlab.com/x4ku/progja
Author: Zach McAuliffe
Author-email: zach.mcauliffe@gmail.com
License: MIT License
Keywords: japanese
Platform: UNKNOWN
Classifier: Development Status :: 3 - Alpha
Classifier: Intended Audience :: Education
Classifier: Intended Audience :: Science/Research
Classifier: License :: OSI Approved :: MIT License
Classifier: License :: OSI Approved :: GNU General Public License v2 (GPLv2)
Classifier: License :: Other/Proprietary License
Classifier: Programming Language :: Python :: 3
License-File: LICENSE
Requires-Dist: pandas (>=1.2)
Requires-Dist: sudachipy (>=0.6.2)
Requires-Dist: sudachidict-core
